extend_noip/__init__.py
extend_noip/__main__.py
extend_noip/config.py
extend_noip/fetch_lastupdate.py
extend_noip/fetch_myservices.py
extend_noip/get_ppbrowser.py
extend_noip/login_noip.py
extend_noip/save_tempfile.py
extend_noip/update_service.py
extend_noip-0.1.1.dist-info/entry_points.txt
extend_noip-0.1.1.dist-info/LICENSE
extend_noip-0.1.1.dist-info/WHEEL
extend_noip-0.1.1.dist-info/METADATA
extend_noip-0.1.1.dist-info/RECORD
