Metadata-Version: 2.1
Name: extend-noip
Version: 0.1.1
Summary: Extend noip dns records for one more month
Home-page: https://github.com/ffreemt/extend-noip
License: MIT
Author: freemt
Requires-Python: >=3.7,<4.0
Classifier: License :: OSI Approved :: MIT License
Classifier: Programming Language :: Python :: 3
Classifier: Programming Language :: Python :: 3.7
Classifier: Programming Language :: Python :: 3.8
Requires-Dist: absl-py (>=0.11.0,<0.12.0)
Requires-Dist: chardet (>=4.0.0,<5.0.0)
Requires-Dist: logzero (>=1.6.3,<2.0.0)
Requires-Dist: more_itertools (>=8.7.0,<9.0.0)
Requires-Dist: pydantic[dotenv] (>=1.7.3,<2.0.0)
Requires-Dist: pyppeteer2 (>=0.2.2,<0.3.0)
Requires-Dist: pyquery (>=1.4.3,<2.0.0)
Project-URL: Repository, https://github.com/ffreemt/extend-noip
